agodzoYTRenderer/__init__.py
agodzoYTRenderer/custom_exception.py
agodzoYTRenderer/logger.py
agodzoYTRenderer/site.py
agodzoYTRenderer/youtube.py
agodzoYTRenderer-0.0.2.dist-info/LICENSE
agodzoYTRenderer-0.0.2.dist-info/METADATA
agodzoYTRenderer-0.0.2.dist-info/WHEEL
agodzoYTRenderer-0.0.2.dist-info/top_level.txt
agodzoYTRenderer-0.0.2.dist-info/RECORD
